{
  "project_info": {
    "project_number": "965555105998",
    "project_id": "guru2-77835",
    "storage_bucket": "guru2-77835.appspot.com"
  },
  "client": [
    {
      "client_info": {
        "mobilesdk_app_id": "1:965555105998:android:09b68dfde63f0ed1df609f",
        "android_client_info": {
          "package_name": "com.example.gurufin"
        }
      },
      "oauth_client": [
        {
          "client_id": "965555105998-8lbsvcinupsdvo6rd7klodcaa865v15o.apps.googleusercontent.com",
          "client_type": 1,
          "android_info": {
            "package_name": "com.example.gurufin",
            "certificate_hash": "5b1f98698aa75dec62b8072c406a68278d6812b4"
          }
        },
        {
          "client_id": "965555105998-fl366flmqacs5oo9jife8rq4jfk5221m.apps.googleusercontent.com",
          "client_type": 3
        }
      ],
      "api_key": [
        {
          "current_key": "AIzaSyC4Vn8NFUI00Q765RHKOsSYYwLOTRhuWwM"
        }
      ],
      "services": {
        "appinvite_service": {
          "other_platform_oauth_client": [
            {
              "client_id": "965555105998-fl366flmqacs5oo9jife8rq4jfk5221m.apps.googleusercontent.com",
              "client_type": 3
            }
          ]
        }
      }
    }
  ],
  "configuration_version": "1"
}